[{"id":"enemy_2002_bearmi","name":"高普尼克","attrs":[{"maxHp":30000,"atk":2000,"def":200,"magicResistance":50,"moveSpeed":0.5,"attackSpeed":100,"baseAttackTime":3.5,"hpRecoveryPerSec":0,"spRecoveryPerSec":0,"massLevel":4,"stunImmune":true,"frozenImmune":true,"levitateImmune":true},{"maxHp":70000,"atk":3000,"def":450},{"maxHp":90000,"atk":4000,"def":550}],"level":"ELITE","tag":null},{"id":"enemy_2001_duckmi","name":"鸭爵","attrs":[{"maxHp":18000,"atk":100,"def":200,"magicResistance":30,"moveSpeed":0.4,"attackSpeed":100,"baseAttackTime":1,"hpRecoveryPerSec":0,"spRecoveryPerSec":0,"massLevel":3,"stunImmune":false,"silenceImmune":true},{"maxHp":35000,"def":300},{"maxHp":45000,"def":400}],"level":"ELITE","tag":null},{"id":"enemy_2034_sythef","name":"流泪小子","attrs":[{"maxHp":8000,"atk":300,"def":150,"magicResistance":20,"moveSpeed":0.8,"attackSpeed":100,"baseAttackTime":2,"massLevel":2},{"maxHp":18000,"atk":500,"baseAttackTime":1.9},{"maxHp":25000,"atk":600,"baseAttackTime":1.8}],"level":"ELITE","tag":null},{"id":"enemy_2056_smedzi","name":"无垠回荡克雷松","attrs":[{"maxHp":80000,"atk":1000,"def":1500,"magicResistance":50,"attackSpeed":100,"baseAttackTime":5,"massLevel":0,"stunImmune":true,"silenceImmune":true,"sleepImmune":true,"frozenImmune":true,"levitateImmune":true}],"level":"BOSS","tag":["collapsal"]},{"id":"enemy_1136_redace_2","name":"“红标”精英渗透者","attrs":[{"maxHp":16000,"atk":500,"def":500,"magicResistance":30,"moveSpeed":1.3,"attackSpeed":100,"baseAttackTime":2,"massLevel":1,"silenceImmune":true}],"level":"ELITE","tag":null},{"id":"enemy_1330_cbrush_2","name":"“肇事者”试做型","attrs":[{"maxHp":28000,"atk":1200,"def":1300,"moveSpeed":1.1,"attackSpeed":100,"baseAttackTime":5,"massLevel":3}],"level":"ELITE","tag":["machine"]},{"id":"enemy_2051_smsha2","name":"空洞雪祀","attrs":[{"maxHp":45000,"atk":750,"def":300,"magicResistance":60,"moveSpeed":2.5,"attackSpeed":100,"baseAttackTime":5,"massLevel":3,"stunImmune":true}],"level":"BOSS","tag":["collapsal"]},{"id":"enemy_2054_smdeer","name":"“萨米的意志”","attrs":[{"maxHp":240000,"atk":800,"def":800,"magicResistance":40,"moveSpeed":1,"attackSpeed":100,"baseAttackTime":6,"massLevel":10,"stunImmune":true,"silenceImmune":true,"sleepImmune":true,"frozenImmune":true,"levitateImmune":true,"disarmedCombatImmune":true}],"level":"BOSS","tag":null},{"id":"enemy_2057_smkght","name":"哈兰杜汗，大地之鞭","attrs":[{"maxHp":180000,"atk":1000,"def":5000,"magicResistance":50,"moveSpeed":0.6,"attackSpeed":100,"baseAttackTime":5,"massLevel":7,"stunImmune":true,"silenceImmune":true,"sleepImmune":true,"frozenImmune":true,"levitateImmune":true}],"level":"BOSS","tag":[]},{"id":"enemy_2058_smlion","name":"路加萨尔古斯，历法之王","attrs":[{"maxHp":180000,"atk":1000,"def":1000,"magicResistance":90,"moveSpeed":0.6,"attackSpeed":100,"baseAttackTime":4,"massLevel":7,"stunImmune":true,"silenceImmune":true,"sleepImmune":true,"frozenImmune":true,"levitateImmune":true}],"level":"BOSS","tag":null},{"id":"enemy_2048_smgrd","name":"“邪魔的利刃”","attrs":[{"maxHp":50000,"atk":800,"def":300,"magicResistance":30,"moveSpeed":0.6,"attackSpeed":100,"baseAttackTime":4,"massLevel":4,"stunImmune":true,"frozenImmune":true}],"level":"BOSS","tag":[]},{"id":"enemy_2055_smlead","name":"“木裂”埃克提尔尼尔","attrs":[{"maxHp":150000,"atk":1000,"def":3000,"magicResistance":30,"moveSpeed":1.1,"attackSpeed":100,"baseAttackTime":2,"massLevel":7,"stunImmune":true,"silenceImmune":true,"sleepImmune":true,"frozenImmune":true,"levitateImmune":false}],"level":"BOSS","tag":["collapsal"]},{"id":"enemy_1328_cbjedi","name":"弧光锋卫","attrs":[{"maxHp":10000,"atk":600,"def":550,"magicResistance":50,"moveSpeed":0.75,"attackSpeed":100,"baseAttackTime":3,"massLevel":1}],"level":"ELITE","tag":[]},{"id":"enemy_2050_smsha","name":"陷落雪祀","attrs":[{"maxHp":40000,"atk":600,"def":300,"magicResistance":60,"moveSpeed":2.5,"attackSpeed":100,"baseAttackTime":5,"massLevel":3,"stunImmune":true}],"level":"BOSS","tag":["collapsal"]},{"id":"enemy_1175_dushdo","name":"深池伙友影刃","attrs":[{"maxHp":25000,"atk":800,"def":350,"magicResistance":0,"moveSpeed":0.8,"attackSpeed":100,"baseAttackTime":2.1,"hpRecoveryPerSec":0,"massLevel":2,"stunImmune":false,"silenceImmune":false}],"level":"ELITE","tag":null},{"id":"enemy_1175_dushdo_2","name":"深池伙友影刃精英","attrs":[{"maxHp":50000,"atk":1100,"def":550,"magicResistance":0,"moveSpeed":0.8,"attackSpeed":100,"baseAttackTime":2.1,"hpRecoveryPerSec":0,"massLevel":2,"stunImmune":false,"silenceImmune":false}],"level":"ELITE","tag":null},{"id":"enemy_1243_ltswar_2","name":"残党正式萨克斯手","attrs":[{"maxHp":30000,"atk":1000,"def":900,"magicResistance":40,"moveSpeed":0.8,"attackSpeed":100,"baseAttackTime":4.5,"massLevel":4}],"level":"ELITE","tag":null},{"id":"enemy_2054_smdeer_b","name":"“萨米的意志”","attrs":[{"maxHp":240000,"atk":800,"def":800,"magicResistance":40,"moveSpeed":1,"attackSpeed":100,"baseAttackTime":6,"hpRecoveryPerSec":0,"spRecoveryPerSec":1,"massLevel":10,"tauntLevel":0,"epDamageResistance":0,"epResistance":0,"stunImmune":true,"silenceImmune":true,"sleepImmune":true,"frozenImmune":true,"levitateImmune":true}],"level":"BOSS","tag":[]},{"id":"enemy_2052_smgia","name":"纠缠藤蔓","attrs":[{"maxHp":90000,"atk":1200,"def":700,"magicResistance":30,"moveSpeed":0.5,"attackSpeed":100,"baseAttackTime":3,"massLevel":5,"silenceImmune":true}],"level":"BOSS","tag":["originiumartscraft"]}]